{
    "$schema": "http://json-schema.org/draft-06/schema", 
    "title": "AST Schema V1", 
    "description": "Structure of an AST object",
    "type": "object",
    "properties": {
        "id": {
            "desceription": "A unique identifier for the current element", 
            "type" : "integer"
        }, 
        "type" : {
            "description": "The type category of the element (component/textnode)",
            "type": "string",
            "enum": ["component"]
        },
        "name" : {
            "description": "The name of the element", 
            "type": "string"
        },
        "properties" : {
            "description": "The properties/attributes of the element", 
            "type": "object", 
            "properties": {
                "name": {
                    "description": "Name of the property", 
                    "type": "string"
                }, 
                "data": {
                    "description": "Object containing data for the particular property", 
                    "type": "object",
                    "properties": {
                    	"type": {
                    		"description": "The evaluation type of the property. Can be value/variable/expression",
                    		"type": "string",
                    		"enum": ["value", "variable", "expression"]
                    	}, 
                    	"value": {
                    		"description": "Property value", 
                    		"type": "string"
                    	}
                    }
                }
            }, 
            "minItems": 1, 
            "uniqueItems": true
        }, 
        "children": {
            "description": "The children of the element.",
            "type": "array", 
            "items": {
            	"anyof": [
            		{"$ref": "#"}, 
            		{
            			"description": "Structure for a textnode", 
            			"type": "object",
            			"properties": {
            				"id": {
            					"desceription": "A unique identifier for the current element", 
            					"id" : "integer"
            				}, 
            				"type": {
            					"description": "The type category of the element (component/textnode)",
            					"type": "string",
            					"enum": ["textnode"]
            				},
            				"value": {
            					"description": "Property value", 
                    			"type": "string"
            				}	
            			},
            			"additionalProperties": false
            		}
            	]
                            }, 
            "uniqueItems": true
        }
    },
    "required" : [ "id", "type", "name"],
    "additionalProperties": false
}